optimization/__init__.py
minimization-0.0.1.dist-info/METADATA
minimization-0.0.1.dist-info/WHEEL
minimization-0.0.1.dist-info/top_level.txt
minimization-0.0.1.dist-info/RECORD
