Metadata-Version: 2.1
Name: minimization
Version: 0.0.1
Summary: optimization
Home-page: https://github.com/netw0rkf10w/optimization.git
Author: Khue Le
Author-email: huudienkhue.le@gmail.com
Project-URL: Bug Tracker, https://github.com/netw0rkf10w/optimization/issues
Classifier: Programming Language :: Python :: 3
Classifier: License :: OSI Approved :: GNU General Public License v3 or later (GPLv3+)
Classifier: Operating System :: OS Independent
Requires-Python: >=3.6
